sudachidict_core/__init__.py
sudachidict_core/resources/LEGAL
sudachidict_core/resources/LICENSE-2.0.txt
sudachidict_core/resources/system.dic
mw_sudachidict_core-20221021.dist-info/LICENSE-2.0.txt
mw_sudachidict_core-20221021.dist-info/METADATA
mw_sudachidict_core-20221021.dist-info/WHEEL
mw_sudachidict_core-20221021.dist-info/top_level.txt
mw_sudachidict_core-20221021.dist-info/RECORD
