Metadata-Version: 2.1
Name: mw-sudachidict-core
Version: 20221021
Summary: Sudachi Dictionary for SudachiPy - Core Edition
Home-page: https://github.com/WorksApplications/SudachiDict
Author: Works Applications
Author-email: sudachi@worksap.co.jp
License: Apache-2.0
Platform: UNKNOWN
License-File: LICENSE-2.0.txt
Requires-Dist: SudachiPy (<0.7,>=0.5)
